AUTHORS.rst
CONTRIBUTING.rst
HISTORY.rst
LICENSE
MANIFEST.in
README.rst
setup.cfg
setup.py
docs/Makefile
docs/authors.rst
docs/conf.py
docs/contributing.rst
docs/history.rst
docs/index.rst
docs/installation.rst
docs/make.bat
docs/readme.rst
docs/usage.rst
submovements/DataProcessing.py
submovements/__init__.py
submovements/fit_submovements.py
submovements.egg-info/PKG-INFO
submovements.egg-info/SOURCES.txt
submovements.egg-info/dependency_links.txt
submovements.egg-info/not-zip-safe
submovements.egg-info/top_level.txt
tests/li_stub_right_11_11.csv
tests/test_submovements.py
tests/dir_with_bad_file_name/li_stub_right_11.csv
tests/good_data/li_square_left_10_16.csv
tests/good_data/li_square_left_10_17.csv
tests/good_data/li_square_left_10_18.csv
tests/good_data/li_square_left_10_20.csv
tests/good_data/li_square_left_10_28.csv
tests/good_data/li_square_left_10_36.csv
tests/good_data/li_square_left_10_48.csv
tests/good_data/li_square_left_1_11.csv
tests/good_data/li_square_right_1_10.csv
tests/good_data/li_square_right_1_21.csv
tests/good_data/li_square_right_1_22.csv
tests/good_data/li_square_right_1_36.csv
tests/good_data/li_square_right_1_38.csv
tests/good_data/li_square_right_1_43.csv
tests/good_data/li_square_right_1_46.csv
tests/good_data/li_square_right_1_48.csv
tests/good_data/li_square_right_1_6.csv
tests/good_data/li_square_right_1_7.csv
tests/good_data/li_square_right_1_9.csv
tests/good_data/li_square_right_2_2.csv
tests/good_data/csv/square_left_10_16_df.csv
tests/good_data/csv/square_left_10_17_df.csv
tests/good_data/csv/square_left_10_18_df.csv
tests/good_data/csv/square_left_10_20_df.csv
tests/good_data/csv/square_left_10_28_df.csv
tests/good_data/csv/square_left_10_36_df.csv
tests/good_data/csv/square_left_10_48_df.csv
tests/good_data/csv/square_left_1_11_df.csv
tests/good_data/csv/square_right_1_10_df.csv
tests/good_data/csv/square_right_1_21_df.csv
tests/good_data/csv/square_right_1_22_df.csv
tests/good_data/csv/square_right_1_36_df.csv
tests/good_data/csv/square_right_1_38_df.csv
tests/good_data/csv/square_right_1_43_df.csv
tests/good_data/csv/square_right_1_46_df.csv
tests/good_data/csv/square_right_1_48_df.csv
